odoo8_addon_document_choose_directory-8.0.1.0.0.99.dev12-py2.7-nspkg.pth
odoo8_addon_document_choose_directory-8.0.1.0.0.99.dev12.dist-info/DESCRIPTION.rst
odoo8_addon_document_choose_directory-8.0.1.0.0.99.dev12.dist-info/METADATA
odoo8_addon_document_choose_directory-8.0.1.0.0.99.dev12.dist-info/RECORD
odoo8_addon_document_choose_directory-8.0.1.0.0.99.dev12.dist-info/WHEEL
odoo8_addon_document_choose_directory-8.0.1.0.0.99.dev12.dist-info/metadata.json
odoo8_addon_document_choose_directory-8.0.1.0.0.99.dev12.dist-info/namespace_packages.txt
odoo8_addon_document_choose_directory-8.0.1.0.0.99.dev12.dist-info/top_level.txt
odoo_addons/document_choose_directory/README.rst
odoo_addons/document_choose_directory/__init__.py
odoo_addons/document_choose_directory/__openerp__.py
odoo_addons/document_choose_directory/controllers/__init__.py
odoo_addons/document_choose_directory/controllers/binary.py
odoo_addons/document_choose_directory/i18n/de.po
odoo_addons/document_choose_directory/i18n/es.po
odoo_addons/document_choose_directory/i18n/fr.po
odoo_addons/document_choose_directory/i18n/fr_CH.po
odoo_addons/document_choose_directory/i18n/it.po
odoo_addons/document_choose_directory/i18n/nl.po
odoo_addons/document_choose_directory/i18n/sl.po
odoo_addons/document_choose_directory/i18n/zh_CN.po
odoo_addons/document_choose_directory/model/__init__.py
odoo_addons/document_choose_directory/model/document_directory.py
odoo_addons/document_choose_directory/model/ir_attachment.py
odoo_addons/document_choose_directory/static/description/icon.png
odoo_addons/document_choose_directory/static/src/css/document_choose_directory.css
odoo_addons/document_choose_directory/static/src/js/document_choose_directory.js
odoo_addons/document_choose_directory/static/src/xml/document_choose_directory.xml
odoo_addons/document_choose_directory/view/document_directory.xml
odoo_addons/document_choose_directory/view/qweb.xml
